procmedia/__init__.py
procmedia/__main__.py
procmedia/detect.py
procmedia/help.py
procmedia/main.py
procmedia/utils.py
procmedia-0.0.8.dist-info/LICENSE.md
procmedia-0.0.8.dist-info/METADATA
procmedia-0.0.8.dist-info/WHEEL
procmedia-0.0.8.dist-info/top_level.txt
procmedia-0.0.8.dist-info/RECORD
