Metadata-Version: 2.1
Name: procmedia
Version: 0.0.8
Summary: Package to applying haarcascades to videos and images
Home-page: https://github.com/miki164/procmedia
Author: miki164
Author-email: miki3867@gmail.com
License: UNKNOWN
Project-URL: Bug Tracker, https://github.com/miki164/procmedia/issues
Platform: UNKNOWN
Classifier: Programming Language :: Python :: 3
Classifier: License :: OSI Approved :: MIT License
Classifier: Operating System :: OS Independent
Requires-Python: >=3.6
Requires-Dist: numpy (==1.20.1)
Requires-Dist: opencv-python (==4.5.1.48)
Requires-Dist: python-magic (==0.4.22)
